aiel/__init__.py
aiel/cli.py
aiel/cli_utils.py
aiel/config.py
aiel/data_plane.py
aiel/errors.py
aiel/roadmap.py
aiel/utilities.py
aiel/auth/api.py
aiel/auth/credentials.py
aiel/commands/_index.py
aiel/commands/auth.py
aiel/commands/config.py
aiel/commands/files.py
aiel/commands/info.py
aiel/commands/repo.py
aiel/commands/.old/auth_doc.py
aiel/commands/.old/config copy.py
aiel/commands/.old/files copy.py
aiel/commands/.old/info copy.py
aiel/commands/.old/repo copy.py
aiel_cli-1.1.5.dist-info/METADATA
aiel_cli-1.1.5.dist-info/WHEEL
aiel_cli-1.1.5.dist-info/entry_points.txt
aiel_cli-1.1.5.dist-info/licenses/LICENSE
aiel_cli-1.1.5.dist-info/RECORD
