Metadata-Version: 2.4
Name: aiel-cli
Version: 1.1.5
Summary: AI Execution Layer CLI
Author-email: Aldenir Flauzino <aldenirsrv@gmail.com>
License: 
License-File: LICENSE
Requires-Python: >=3.10
Requires-Dist: httpx>=0.27.0
Requires-Dist: questionary>=2.0.0
Requires-Dist: rich>=13.7.1
Requires-Dist: typer>=0.12.3
Provides-Extra: dev
Requires-Dist: pytest-cov>=4.1; extra == 'dev'
Requires-Dist: pytest>=7.4; extra == 'dev'
